up_paraspace/__about__.py
up_paraspace/__init__.py
up_paraspace/classical_conversion.py
up_paraspace/conversion_error.py
up_paraspace/timelines_conversion.py
up_paraspace/tms_example.py
up_paraspace/up_paraspace.py
up_paraspace-0.0.12.dist-info/METADATA
up_paraspace-0.0.12.dist-info/WHEEL
up_paraspace-0.0.12.dist-info/licenses/LICENSE.txt
up_paraspace-0.0.12.dist-info/RECORD
