Metadata-Version: 2.1
Name: up-paraspace
Version: 0.0.12
Project-URL: Documentation, https://github.com/luteberget/up-paraspace#readme
Project-URL: Issues, https://github.com/luteberget/up-paraspace/issues
Project-URL: Source, https://github.com/luteberget/up-paraspace
Author-email: Bjørnar Luteberget <bjornar.luteberget@sintef.no>
License-Expression: MIT
License-File: LICENSE.txt
Classifier: Development Status :: 4 - Beta
Classifier: Programming Language :: Python
Classifier: Programming Language :: Python :: 3.10
Classifier: Programming Language :: Python :: 3.11
Classifier: Programming Language :: Python :: Implementation :: CPython
Classifier: Programming Language :: Python :: Implementation :: PyPy
Requires-Python: >=3.10
Requires-Dist: pyparaspace==0.1.8
Requires-Dist: unified-planning~=1.0
Requires-Dist: up-pyperplan~=1.0
